easyManhattan/__init__.py
easyManhattan/__main__.py
easyManhattan/double_files.py
easyManhattan/run.py
easyManhattan/single_files.py
easyManhattan-1.0.3.dist-info/LICENSE
easyManhattan-1.0.3.dist-info/METADATA
easyManhattan-1.0.3.dist-info/PKG-INFO.orig
easyManhattan-1.0.3.dist-info/WHEEL
easyManhattan-1.0.3.dist-info/top_level.txt
easyManhattan-1.0.3.dist-info/RECORD
