Metadata-Version: 2.1
Name: easyManhattan
Version: 1.0.3
Summary: An easy-to-use package to generate Manhattan plots
Home-page: https://github.com/jamesjisu/easyManhattan
Author: James Han
Author-email: jamesjisu@gmail.com
License: UNKNOWN
Platform: UNKNOWN
Classifier: Programming Language :: Python :: 3
Classifier: License :: OSI Approved :: MIT License
Classifier: Operating System :: OS Independent
Requires-Python: >=3.6
Requires-Dist: numpy
Requires-Dist: pandas
Requires-Dist: matplotlib
